Metadata-Version: 2.1
Name: http-token-auth
Version: 0.1.0
Summary: Python implementation of token backend for HTTP and Oauth sessions
Home-page: https://gitlab.com/defalsify/python-http-hoba-auth
Author: Louis Holbrook
Author-email: dev@holbrook.no
License: WTFPL
Keywords: http,internet,authentication
Classifier: Programming Language :: Python :: 3
Classifier: Operating System :: OS Independent
Classifier: Development Status :: 3 - Alpha
Classifier: Intended Audience :: Developers
Classifier: License :: OSI Approved :: GNU General Public License v3 or later (GPLv3+)
Classifier: Topic :: Software Development :: Libraries
Classifier: Topic :: Internet
Requires-Python: >=3.6
License-File: LICENSE
